docs/source/conf.py
numba_rvsdg/__init__.py
numba_rvsdg/core/transformations.py
numba_rvsdg/core/utils.py
numba_rvsdg/core/datastructures/ast_transforms.py
numba_rvsdg/core/datastructures/basic_block.py
numba_rvsdg/core/datastructures/block_names.py
numba_rvsdg/core/datastructures/byte_flow.py
numba_rvsdg/core/datastructures/flow_info.py
numba_rvsdg/core/datastructures/scfg.py
numba_rvsdg/networkx_vendored/scc.py
numba_rvsdg/rendering/rendering.py
numba_rvsdg/tests/mock_asm.py
numba_rvsdg/tests/simulator.py
numba_rvsdg/tests/test_ast_transforms.py
numba_rvsdg/tests/test_byteflow.py
numba_rvsdg/tests/test_figures.py
numba_rvsdg/tests/test_mock_asm.py
numba_rvsdg/tests/test_rendering.py
numba_rvsdg/tests/test_scc.py
numba_rvsdg/tests/test_scfg.py
numba_rvsdg/tests/test_simulate.py
numba_rvsdg/tests/test_transforms.py
numba_rvsdg/tests/test_utils.py
numba_rvsdg-0.0.6.dist-info/LICENSE
numba_rvsdg-0.0.6.dist-info/METADATA
numba_rvsdg-0.0.6.dist-info/WHEEL
numba_rvsdg-0.0.6.dist-info/top_level.txt
numba_rvsdg-0.0.6.dist-info/RECORD
