Metadata-Version: 2.2
Name: numba_rvsdg
Version: 0.0.6
Summary: Numba Compatible RVSDG utilities
Author-email: Numba Developers <none@none.none>
License: BSD-2-Clause
Keywords: numba
Classifier: Programming Language :: Python :: 3
Requires-Python: >=3.11
License-File: LICENSE
Requires-Dist: graphviz
Requires-Dist: pyyaml
Provides-Extra: dev
Requires-Dist: sphinx; extra == "dev"
Requires-Dist: myst-parser; extra == "dev"
Requires-Dist: furo; extra == "dev"
Requires-Dist: pytest; extra == "dev"
Requires-Dist: sphinx-rtd-theme; extra == "dev"
